mvim/__init__.py
mvim/__main__.py
mvim/main.py
mvim/mvim.py
MVim-0.2.0.dist-info/LICENSE
MVim-0.2.0.dist-info/METADATA
MVim-0.2.0.dist-info/WHEEL
MVim-0.2.0.dist-info/entry_points.txt
MVim-0.2.0.dist-info/top_level.txt
MVim-0.2.0.dist-info/RECORD
