Metadata-Version: 2.1
Name: MVim
Version: 0.2.0
Summary: Tool to rename files using vim to edit their names
Author-email: Élie Bouttier <elie+mvim@bouttier.eu>
Project-URL: Source, https://github.com/bouttier/mvim
Project-URL: Tracker, https://github.com/bouttier/mvim/issues
Classifier: Development Status :: 4 - Beta
Classifier: Environment :: Console
Classifier: License :: OSI Approved :: Apache Software License
Classifier: Programming Language :: Python :: 3.6
Classifier: Programming Language :: Python :: 3.7
Classifier: Programming Language :: Python :: 3.8
Classifier: Programming Language :: Python :: 3.9
Classifier: Programming Language :: Python :: 3.10
Classifier: Topic :: Utilities
Requires-Python: >=3.6
License-File: LICENSE
